pystardog-0.19.0.dist-info/licenses/LICENSE
stardog/__init__.py
stardog/admin.py
stardog/connection.py
stardog/content.py
stardog/content_types.py
stardog/exceptions.py
stardog/results.py
stardog/utils.py
stardog/cloud/__init__.py
stardog/cloud/client.py
stardog/cloud/exceptions.py
stardog/cloud/voicebox.py
stardog/http/__init__.py
stardog/http/client.py
pystardog-0.19.0.dist-info/METADATA
pystardog-0.19.0.dist-info/WHEEL
pystardog-0.19.0.dist-info/top_level.txt
pystardog-0.19.0.dist-info/RECORD
